{
  "ocid": "woodpecker-coalindia-2026_BCCL_360602_1",
  "releases": [
    {
      "ocid": "woodpecker-coalindia-2026_BCCL_360602_1",
      "id": "woodpecker-coalindia-2026_BCCL_360602_1-0001",
      "date": "2026-06-01T00:00:00Z",
      "tag": [
        "tender"
      ],
      "initiationType": "tender",
      "buyer": {
        "name": "Bharat Coking Coal Limited||BCCL_SIJUA AREA",
        "id": "IN-ORG-bharat-coking-coal-limited-bccl-sijua-ar"
      },
      "tender": {
        "id": "2026_BCCL_360602_1",
        "title": "For Fabrication and installation of 20ftx15ft Shed Height 10ft for Transformer Room at Kankanee Colliery under Sijua Area",
        "status": "active",
        "procuringEntity": {
          "name": "Bharat Coking Coal Limited||BCCL_SIJUA AREA",
          "id": "IN-ORG-bharat-coking-coal-limited-bccl-sijua-ar"
        },
        "mainProcurementCategory": "works",
        "value": {
          "amount": 293791,
          "currency": "INR"
        },
        "tenderPeriod": {
          "endDate": "2026-06-11T00:00:00Z"
        },
        "description": "For Fabrication and installation of 20ftx15ft Shed Height 10ft for Transformer Room at Kankanee Colliery under Sijua Area"
      },
      "documents": [
        {
          "id": "woodpecker-coalindia-2026_BCCL_360602_1-0001-record",
          "documentType": "tenderNotice",
          "title": "Captured tender record (text) — 2026_BCCL_360602_1",
          "url": "/files/0bd2904c3101a368bb8ff824ff7b0f7a09ddeeb0e709b2d4990c0155aae43f4d.txt",
          "sourceUrl": "https://coalindiatenders.nic.in/nicgep/app?component=%24DirectLink&page=FrontEndListTendersbyDate&service=direct&session=T&sp=SlxhPnEhYVaOTRmGq2kBhfg%3D%3D",
          "sourceAlive": true,
          "sha256": "0bd2904c3101a368bb8ff824ff7b0f7a09ddeeb0e709b2d4990c0155aae43f4d",
          "format": "text/plain",
          "textUrl": "/files/0bd2904c3101a368bb8ff824ff7b0f7a09ddeeb0e709b2d4990c0155aae43f4d.txt",
          "extractionMethod": "raw"
        },
        {
          "id": "woodpecker-coalindia-2026_BCCL_360602_1-0001-doc-1",
          "documentType": "biddingDocuments",
          "title": "Tendernotice_1.pdf",
          "url": null,
          "sourceUrl": "https://coalindiatenders.nic.in/nicgep/app?component=%24DirectLink&page=FrontEndListTendersbyDate&service=direct&session=T&sp=SlxhPnEhYVaOTRmGq2kBhfg%3D%3D",
          "sourceAlive": false,
          "sha256": null,
          "format": "application/pdf",
          "textUrl": null,
          "extractionMethod": "none"
        }
      ]
    }
  ],
  "compiledRelease": {
    "ocid": "woodpecker-coalindia-2026_BCCL_360602_1",
    "tender": {
      "id": "2026_BCCL_360602_1",
      "title": "For Fabrication and installation of 20ftx15ft Shed Height 10ft for Transformer Room at Kankanee Colliery under Sijua Area",
      "status": "active",
      "procuringEntity": {
        "name": "Bharat Coking Coal Limited||BCCL_SIJUA AREA",
        "id": "IN-ORG-bharat-coking-coal-limited-bccl-sijua-ar"
      },
      "mainProcurementCategory": "works",
      "value": {
        "amount": 293791,
        "currency": "INR"
      },
      "tenderPeriod": {
        "endDate": "2026-06-11T00:00:00Z"
      },
      "description": "For Fabrication and installation of 20ftx15ft Shed Height 10ft for Transformer Room at Kankanee Colliery under Sijua Area"
    },
    "buyer": {
      "name": "Bharat Coking Coal Limited||BCCL_SIJUA AREA",
      "id": "IN-ORG-bharat-coking-coal-limited-bccl-sijua-ar"
    },
    "date": "2026-06-01T00:00:00Z",
    "tag": [
      "compiled"
    ],
    "documents": [
      {
        "id": "woodpecker-coalindia-2026_BCCL_360602_1-0001-record",
        "documentType": "tenderNotice",
        "title": "Captured tender record (text) — 2026_BCCL_360602_1",
        "url": "/files/0bd2904c3101a368bb8ff824ff7b0f7a09ddeeb0e709b2d4990c0155aae43f4d.txt",
        "sourceUrl": "https://coalindiatenders.nic.in/nicgep/app?component=%24DirectLink&page=FrontEndListTendersbyDate&service=direct&session=T&sp=SlxhPnEhYVaOTRmGq2kBhfg%3D%3D",
        "sourceAlive": true,
        "sha256": "0bd2904c3101a368bb8ff824ff7b0f7a09ddeeb0e709b2d4990c0155aae43f4d",
        "format": "text/plain",
        "textUrl": "/files/0bd2904c3101a368bb8ff824ff7b0f7a09ddeeb0e709b2d4990c0155aae43f4d.txt",
        "extractionMethod": "raw"
      },
      {
        "id": "woodpecker-coalindia-2026_BCCL_360602_1-0001-doc-1",
        "documentType": "biddingDocuments",
        "title": "Tendernotice_1.pdf",
        "url": null,
        "sourceUrl": "https://coalindiatenders.nic.in/nicgep/app?component=%24DirectLink&page=FrontEndListTendersbyDate&service=direct&session=T&sp=SlxhPnEhYVaOTRmGq2kBhfg%3D%3D",
        "sourceAlive": false,
        "sha256": null,
        "format": "application/pdf",
        "textUrl": null,
        "extractionMethod": "none"
      }
    ]
  },
  "amendments": [],
  "observations": [
    {
      "ocid": "woodpecker-coalindia-2026_BCCL_360602_1",
      "observedAt": "2026-06-11T03:59:24Z",
      "witness": "woodpecker:coalindia",
      "availability": "present",
      "stateHash": "6244d7a417a46d6576887a7cc54e5022bbe1d3804190ccdd9361ee6d9d931375",
      "documents": [
        {
          "id": "woodpecker-coalindia-2026_BCCL_360602_1-0001-record",
          "sha256": "0bd2904c3101a368bb8ff824ff7b0f7a09ddeeb0e709b2d4990c0155aae43f4d"
        }
      ],
      "snapshotUrl": "/files/625fa315f69df519f8662f93e1f52f796e8a89f6fbb3676f0c068a7bf41c6332.json",
      "undeclaredChange": false
    }
  ],
  "observedSummary": {
    "count": 1,
    "firstObserved": "2026-06-11T03:59:24Z",
    "lastObserved": "2026-06-11T03:59:24Z",
    "undeclaredChangeCount": 0,
    "pulled": false
  }
}
