{
  "ocid": "woodpecker-delhi-2026_PWD_292532_1",
  "releases": [
    {
      "ocid": "woodpecker-delhi-2026_PWD_292532_1",
      "id": "woodpecker-delhi-2026_PWD_292532_1-0001",
      "date": "2026-06-03T00:00:00Z",
      "tag": [
        "tender"
      ],
      "initiationType": "tender",
      "buyer": {
        "name": "Public Works Department||CE/SE/M1-M14||EE/M141(N)",
        "id": "IN-ORG-public-works-department-ce-se-m1-m14-ee-"
      },
      "tender": {
        "id": "2026_PWD_292532_1",
        "title": "A/R and M/O work of various roads under SD-23, Jaffarpur, SWR-2, PWD, New Delhi (SH providing and laying 200 mm dia HDPE pipe from Khera More to RCC New Drain (Both Sides) on Rao Laxmi Chand Marg (ID-1174) to prevent the water logging at Som Bazar an",
        "status": "active",
        "procuringEntity": {
          "name": "Public Works Department||CE/SE/M1-M14||EE/M141(N)",
          "id": "IN-ORG-public-works-department-ce-se-m1-m14-ee-"
        },
        "mainProcurementCategory": "works",
        "value": {
          "amount": 12482079,
          "currency": "INR"
        },
        "tenderPeriod": {
          "endDate": "2026-06-11T00:00:00Z"
        },
        "description": "A/R and M/O work of various roads under SD-23, Jaffarpur, SWR-2, PWD, New Delhi (SH providing and laying 200 mm dia HDPE pipe from Khera More to RCC New Drain (Both Sides) on Rao Laxmi Chand Marg (ID-1174) to prevent the water logging at Som Bazar an"
      },
      "documents": [
        {
          "id": "woodpecker-delhi-2026_PWD_292532_1-0001-record",
          "documentType": "tenderNotice",
          "title": "Captured tender record (text) — 2026_PWD_292532_1",
          "url": "/files/8258f0e18194a554ad7067b52f4e6ed19def68bbb589eec45d1e16d441de0dbe.txt",
          "sourceUrl": "https://govtprocurement.delhi.gov.in/nicgep/app?component=%24DirectLink&page=FrontEndListTendersbyDate&service=direct&session=T&sp=StQT941ClsidA02kUKlMKEg%3D%3D",
          "sourceAlive": true,
          "sha256": "8258f0e18194a554ad7067b52f4e6ed19def68bbb589eec45d1e16d441de0dbe",
          "format": "text/plain",
          "textUrl": "/files/8258f0e18194a554ad7067b52f4e6ed19def68bbb589eec45d1e16d441de0dbe.txt",
          "extractionMethod": "raw"
        },
        {
          "id": "woodpecker-delhi-2026_PWD_292532_1-0001-doc-1",
          "documentType": "biddingDocuments",
          "title": "Tendernotice_1.pdf",
          "url": null,
          "sourceUrl": "https://govtprocurement.delhi.gov.in/nicgep/app?component=%24DirectLink&page=FrontEndListTendersbyDate&service=direct&session=T&sp=StQT941ClsidA02kUKlMKEg%3D%3D",
          "sourceAlive": false,
          "sha256": null,
          "format": "application/pdf",
          "textUrl": null,
          "extractionMethod": "none"
        }
      ]
    }
  ],
  "compiledRelease": {
    "ocid": "woodpecker-delhi-2026_PWD_292532_1",
    "tender": {
      "id": "2026_PWD_292532_1",
      "title": "A/R and M/O work of various roads under SD-23, Jaffarpur, SWR-2, PWD, New Delhi (SH providing and laying 200 mm dia HDPE pipe from Khera More to RCC New Drain (Both Sides) on Rao Laxmi Chand Marg (ID-1174) to prevent the water logging at Som Bazar an",
      "status": "active",
      "procuringEntity": {
        "name": "Public Works Department||CE/SE/M1-M14||EE/M141(N)",
        "id": "IN-ORG-public-works-department-ce-se-m1-m14-ee-"
      },
      "mainProcurementCategory": "works",
      "value": {
        "amount": 12482079,
        "currency": "INR"
      },
      "tenderPeriod": {
        "endDate": "2026-06-11T00:00:00Z"
      },
      "description": "A/R and M/O work of various roads under SD-23, Jaffarpur, SWR-2, PWD, New Delhi (SH providing and laying 200 mm dia HDPE pipe from Khera More to RCC New Drain (Both Sides) on Rao Laxmi Chand Marg (ID-1174) to prevent the water logging at Som Bazar an"
    },
    "buyer": {
      "name": "Public Works Department||CE/SE/M1-M14||EE/M141(N)",
      "id": "IN-ORG-public-works-department-ce-se-m1-m14-ee-"
    },
    "date": "2026-06-03T00:00:00Z",
    "tag": [
      "compiled"
    ],
    "documents": [
      {
        "id": "woodpecker-delhi-2026_PWD_292532_1-0001-record",
        "documentType": "tenderNotice",
        "title": "Captured tender record (text) — 2026_PWD_292532_1",
        "url": "/files/8258f0e18194a554ad7067b52f4e6ed19def68bbb589eec45d1e16d441de0dbe.txt",
        "sourceUrl": "https://govtprocurement.delhi.gov.in/nicgep/app?component=%24DirectLink&page=FrontEndListTendersbyDate&service=direct&session=T&sp=StQT941ClsidA02kUKlMKEg%3D%3D",
        "sourceAlive": true,
        "sha256": "8258f0e18194a554ad7067b52f4e6ed19def68bbb589eec45d1e16d441de0dbe",
        "format": "text/plain",
        "textUrl": "/files/8258f0e18194a554ad7067b52f4e6ed19def68bbb589eec45d1e16d441de0dbe.txt",
        "extractionMethod": "raw"
      },
      {
        "id": "woodpecker-delhi-2026_PWD_292532_1-0001-doc-1",
        "documentType": "biddingDocuments",
        "title": "Tendernotice_1.pdf",
        "url": null,
        "sourceUrl": "https://govtprocurement.delhi.gov.in/nicgep/app?component=%24DirectLink&page=FrontEndListTendersbyDate&service=direct&session=T&sp=StQT941ClsidA02kUKlMKEg%3D%3D",
        "sourceAlive": false,
        "sha256": null,
        "format": "application/pdf",
        "textUrl": null,
        "extractionMethod": "none"
      }
    ]
  },
  "amendments": [],
  "observations": [
    {
      "ocid": "woodpecker-delhi-2026_PWD_292532_1",
      "observedAt": "2026-06-11T03:27:16Z",
      "witness": "woodpecker:delhi",
      "availability": "present",
      "stateHash": "cb3388341764b6cc652e536b14f79cc2cc8c222a17daa9f4778d51b19d403c95",
      "documents": [
        {
          "id": "woodpecker-delhi-2026_PWD_292532_1-0001-record",
          "sha256": "8258f0e18194a554ad7067b52f4e6ed19def68bbb589eec45d1e16d441de0dbe"
        }
      ],
      "snapshotUrl": "/files/88a9e379ee6d8e3cd32c8a4b5ec066a684347aed9719f6e5019ac0164f7f015c.json",
      "undeclaredChange": false
    }
  ],
  "observedSummary": {
    "count": 1,
    "firstObserved": "2026-06-11T03:27:16Z",
    "lastObserved": "2026-06-11T03:27:16Z",
    "undeclaredChangeCount": 0,
    "pulled": false
  }
}
