{
  "documents": [
    {
      "id": "woodpecker-himachal-2026_HPIPH_135851_1-0001-record",
      "sourceAlive": true,
      "title": "Captured tender record (text) — 2026_HPIPH_135851_1"
    },
    {
      "id": "woodpecker-himachal-2026_HPIPH_135851_1-0001-doc-1",
      "sourceAlive": false,
      "title": "Tendernotice_1.pdf"
    }
  ],
  "event": "published",
  "portalTenderId": "2026_HPIPH_135851_1",
  "reference": "No.JSV-RD-AB-Tnd/2026- 1815-50 dt05.06.2026",
  "source": "live",
  "tender": {
    "description": "SH R R Providing and fixing of fencing and protection work to P well and P House.",
    "id": "2026_HPIPH_135851_1",
    "mainProcurementCategory": "works",
    "procuringEntity": {
      "id": "IN-ORG-hp-irrigation-and-public-health-rohru-ci",
      "name": "HP Irrigation and Public Health||Rohru Circle,Irrigation and Public Health,HP||Rohru,Irrigation and Public Health,HP"
    },
    "status": "active",
    "tenderPeriod": {
      "endDate": "2026-06-11T00:00:00Z"
    },
    "title": "SH R R Providing and fixing of fencing and protection work to P well and P House.",
    "value": {
      "amount": 1630082,
      "currency": "INR"
    }
  }
}