{
  "documents": [
    {
      "id": "woodpecker-uttarakhand-2026_pwd_96183_1-0001-record",
      "sourceAlive": true,
      "title": "Captured tender record (text) — 2026_pwd_96183_1"
    },
    {
      "id": "woodpecker-uttarakhand-2026_pwd_96183_1-0001-doc-1",
      "sourceAlive": false,
      "title": "Tendernotice_1.pdf"
    }
  ],
  "event": "published",
  "portalTenderId": "2026_pwd_96183_1",
  "reference": "3071/1C-9/2026, Dated 30/05/2026",
  "source": "live",
  "tender": {
    "description": "Renewal by SDBC on following motor roads under Mussoorie Constituency under Annual Repair (i) Dehradun Kimadi Lambidhar Motilal Nehru Cart Mackenzie Hollock Company Garden road (ii) Rajpur to Mussoorie road via Snow View Jharipani Barlowgunj road.",
    "id": "2026_pwd_96183_1",
    "mainProcurementCategory": "works",
    "procuringEntity": {
      "id": "IN-ORG-pwd-9th-circle-dehradun",
      "name": "PWD||9th Circle Dehradun"
    },
    "status": "active",
    "tenderPeriod": {
      "endDate": "2026-06-12T00:00:00Z"
    },
    "title": "Renewal by SDBC on following motor roads under Mussoorie Constituency under Annual Repair (i) Dehradun Kimadi Lambidhar Motilal Nehru Cart Mackenzie Hollock Company Garden road (ii) Rajpur to Mussoorie road via Snow View Jharipani Barlowgunj road.",
    "value": {
      "amount": 15467000,
      "currency": "INR"
    }
  }
}