{
  "documents": [
    {
      "id": "woodpecker-uttarpradesh-2026_UPCDS_1145869_1-0001-record",
      "sourceAlive": true,
      "title": "Captured tender record (text) — 2026_UPCDS_1145869_1"
    },
    {
      "id": "woodpecker-uttarpradesh-2026_UPCDS_1145869_1-0001-doc-1",
      "sourceAlive": false,
      "title": "Tendernotice_1.pdf"
    }
  ],
  "event": "published",
  "portalTenderId": "2026_UPCDS_1145869_1",
  "reference": "986/M-18/227 Dated 30/04/2026",
  "source": "live",
  "tender": {
    "description": "As per tender documents",
    "id": "2026_UPCDS_1145869_1",
    "mainProcurementCategory": "works",
    "procuringEntity": {
      "id": "IN-ORG-construction-and-design-services-up-jal-",
      "name": "Construction and Design Services UP Jal Nigam||C.G.M. (III) Lucknow||G.M. (01) Lucknow||Unit-18 Moradabad"
    },
    "status": "active",
    "tenderPeriod": {
      "endDate": "2026-06-05T00:00:00Z"
    },
    "title": "As per tender documents",
    "value": {
      "amount": 3993000,
      "currency": "INR"
    }
  }
}