{
  "documents": [
    {
      "id": "woodpecker-coalindia-2026_ECL_360525_1-0001-record",
      "sourceAlive": true,
      "title": "Captured tender record (text) — 2026_ECL_360525_1"
    },
    {
      "id": "woodpecker-coalindia-2026_ECL_360525_1-0001-doc-1",
      "sourceAlive": false,
      "title": "Tendernotice_1.pdf"
    }
  ],
  "event": "published",
  "portalTenderId": "2026_ECL_360525_1",
  "reference": "GM-PND/EandM/26-27/32/2138 dated 28/05/2026",
  "source": "live",
  "tender": {
    "description": "Preparation of roof bolts by threading for Khottadih colliery",
    "id": "2026_ECL_360525_1",
    "mainProcurementCategory": "works",
    "procuringEntity": {
      "id": "IN-ORG-eastern-coalfields-limited-ecl-pandavesw",
      "name": "Eastern Coalfields Limited||ECL_Pandaveswar area"
    },
    "status": "active",
    "tenderPeriod": {
      "endDate": "2026-06-09T00:00:00Z"
    },
    "title": "Preparation of roof bolts by threading for Khottadih colliery",
    "value": {
      "amount": 917766,
      "currency": "INR"
    }
  }
}