{
  "documents": [
    {
      "id": "woodpecker-rajasthan-2026_DLB_561583_8-0001-record",
      "sourceAlive": true,
      "title": "Captured tender record (text) — 2026_DLB_561583_8"
    },
    {
      "id": "woodpecker-rajasthan-2026_DLB_561583_8-0001-doc-1",
      "sourceAlive": false,
      "title": "Tendernotice_1.pdf"
    }
  ],
  "event": "published",
  "portalTenderId": "2026_DLB_561583_8",
  "reference": "NPK/2026-27/232",
  "source": "live",
  "tender": {
    "description": "Main road construction work from Sundarpura Road to the crematoriums",
    "id": "2026_DLB_561583_8",
    "mainProcurementCategory": "works",
    "procuringEntity": {
      "id": "IN-ORG-dlb-dy-dr-jaipur-eo-bansur",
      "name": "DLB||Dy.DR-Jaipur||EO- BANSUR"
    },
    "status": "active",
    "tenderPeriod": {
      "endDate": "2026-06-05T00:00:00Z"
    },
    "title": "Main road construction work from Sundarpura Road to the crematoriums",
    "value": {
      "amount": 3217000,
      "currency": "INR"
    }
  }
}