{
  "ocid": "woodpecker-rajasthan-2026_PRD_563716_1",
  "releases": [
    {
      "ocid": "woodpecker-rajasthan-2026_PRD_563716_1",
      "id": "woodpecker-rajasthan-2026_PRD_563716_1-0001",
      "date": "2026-05-30T00:00:00Z",
      "tag": [
        "tender"
      ],
      "initiationType": "tender",
      "buyer": {
        "name": "Panchayati Raj Department||Secretary and Commissioner||CEO- JAIPUR||BDO-SHAHPURA",
        "id": "IN-ORG-panchayati-raj-department-secretary-and-"
      },
      "tender": {
        "id": "2026_PRD_563716_1",
        "title": "SUPPLY OF CONSTRUCTION MATERIAL AND PROVIDING EQUIPMENT IN GRAM PANCHYAT BILANDARPUR OF PANCHYAT SAMITI SHAHPURA, JAIPUR",
        "status": "active",
        "procuringEntity": {
          "name": "Panchayati Raj Department||Secretary and Commissioner||CEO- JAIPUR||BDO-SHAHPURA",
          "id": "IN-ORG-panchayati-raj-department-secretary-and-"
        },
        "mainProcurementCategory": "works",
        "value": {
          "amount": 9000000,
          "currency": "INR"
        },
        "tenderPeriod": {
          "endDate": "2026-06-10T00:00:00Z"
        },
        "description": "SUPPLY OF CONSTRUCTION MATERIAL AND PROVIDING EQUIPMENT IN GRAM PANCHYAT BILANDARPUR OF PANCHYAT SAMITI SHAHPURA, JAIPUR"
      },
      "documents": [
        {
          "id": "woodpecker-rajasthan-2026_PRD_563716_1-0001-record",
          "documentType": "tenderNotice",
          "title": "Captured tender record (text) — 2026_PRD_563716_1",
          "url": "/files/e010cb5a0188dba451eb12090ce48d20229d0faaf056bfd1b004e60d23a7556e.txt",
          "sourceUrl": "https://eproc.rajasthan.gov.in/nicgep/app?component=%24DirectLink&page=FrontEndListTendersbyDate&service=direct&session=T&sp=S8pqyUAVqLbmotlX2AUoWww%3D%3D",
          "sourceAlive": true,
          "sha256": "e010cb5a0188dba451eb12090ce48d20229d0faaf056bfd1b004e60d23a7556e",
          "format": "text/plain",
          "textUrl": "/files/e010cb5a0188dba451eb12090ce48d20229d0faaf056bfd1b004e60d23a7556e.txt",
          "extractionMethod": "raw"
        },
        {
          "id": "woodpecker-rajasthan-2026_PRD_563716_1-0001-doc-1",
          "documentType": "biddingDocuments",
          "title": "Tendernotice_1.pdf",
          "url": null,
          "sourceUrl": "https://eproc.rajasthan.gov.in/nicgep/app?component=%24DirectLink&page=FrontEndListTendersbyDate&service=direct&session=T&sp=S8pqyUAVqLbmotlX2AUoWww%3D%3D",
          "sourceAlive": false,
          "sha256": null,
          "format": "application/pdf",
          "textUrl": null,
          "extractionMethod": "none"
        }
      ]
    }
  ],
  "compiledRelease": {
    "ocid": "woodpecker-rajasthan-2026_PRD_563716_1",
    "tender": {
      "id": "2026_PRD_563716_1",
      "title": "SUPPLY OF CONSTRUCTION MATERIAL AND PROVIDING EQUIPMENT IN GRAM PANCHYAT BILANDARPUR OF PANCHYAT SAMITI SHAHPURA, JAIPUR",
      "status": "active",
      "procuringEntity": {
        "name": "Panchayati Raj Department||Secretary and Commissioner||CEO- JAIPUR||BDO-SHAHPURA",
        "id": "IN-ORG-panchayati-raj-department-secretary-and-"
      },
      "mainProcurementCategory": "works",
      "value": {
        "amount": 9000000,
        "currency": "INR"
      },
      "tenderPeriod": {
        "endDate": "2026-06-10T00:00:00Z"
      },
      "description": "SUPPLY OF CONSTRUCTION MATERIAL AND PROVIDING EQUIPMENT IN GRAM PANCHYAT BILANDARPUR OF PANCHYAT SAMITI SHAHPURA, JAIPUR"
    },
    "buyer": {
      "name": "Panchayati Raj Department||Secretary and Commissioner||CEO- JAIPUR||BDO-SHAHPURA",
      "id": "IN-ORG-panchayati-raj-department-secretary-and-"
    },
    "date": "2026-05-30T00:00:00Z",
    "tag": [
      "compiled"
    ],
    "documents": [
      {
        "id": "woodpecker-rajasthan-2026_PRD_563716_1-0001-record",
        "documentType": "tenderNotice",
        "title": "Captured tender record (text) — 2026_PRD_563716_1",
        "url": "/files/e010cb5a0188dba451eb12090ce48d20229d0faaf056bfd1b004e60d23a7556e.txt",
        "sourceUrl": "https://eproc.rajasthan.gov.in/nicgep/app?component=%24DirectLink&page=FrontEndListTendersbyDate&service=direct&session=T&sp=S8pqyUAVqLbmotlX2AUoWww%3D%3D",
        "sourceAlive": true,
        "sha256": "e010cb5a0188dba451eb12090ce48d20229d0faaf056bfd1b004e60d23a7556e",
        "format": "text/plain",
        "textUrl": "/files/e010cb5a0188dba451eb12090ce48d20229d0faaf056bfd1b004e60d23a7556e.txt",
        "extractionMethod": "raw"
      },
      {
        "id": "woodpecker-rajasthan-2026_PRD_563716_1-0001-doc-1",
        "documentType": "biddingDocuments",
        "title": "Tendernotice_1.pdf",
        "url": null,
        "sourceUrl": "https://eproc.rajasthan.gov.in/nicgep/app?component=%24DirectLink&page=FrontEndListTendersbyDate&service=direct&session=T&sp=S8pqyUAVqLbmotlX2AUoWww%3D%3D",
        "sourceAlive": false,
        "sha256": null,
        "format": "application/pdf",
        "textUrl": null,
        "extractionMethod": "none"
      }
    ]
  },
  "amendments": [],
  "observations": [
    {
      "ocid": "woodpecker-rajasthan-2026_PRD_563716_1",
      "observedAt": "2026-06-10T03:17:52Z",
      "witness": "woodpecker:rajasthan",
      "availability": "present",
      "stateHash": "ec051d38819e70a87a0e61e699f20cdfabcb013588f90f6485b9b008fd23446c",
      "documents": [
        {
          "id": "woodpecker-rajasthan-2026_PRD_563716_1-0001-record",
          "sha256": "e010cb5a0188dba451eb12090ce48d20229d0faaf056bfd1b004e60d23a7556e"
        }
      ],
      "snapshotUrl": "/files/9b936f4d29275b12a8d53ce3d631d9fe6029e6e65d0f7a0d238ebbcd41cc2682.json",
      "undeclaredChange": false
    }
  ],
  "observedSummary": {
    "count": 1,
    "firstObserved": "2026-06-10T03:17:52Z",
    "lastObserved": "2026-06-10T03:17:52Z",
    "undeclaredChangeCount": 0,
    "pulled": false
  }
}
