{
  "ocid": "woodpecker-kerala-2026_KCMMF_852123_1",
  "id": "woodpecker-kerala-2026_KCMMF_852123_1-0001",
  "date": "2026-05-21T00:00:00Z",
  "tag": [
    "tender"
  ],
  "initiationType": "tender",
  "buyer": {
    "name": "Kerala Co-operative Milk Marketing Federation Ltd||Trivandrum Regional Co-operative Milk Producers Union Ltd||TRCMPU Ltd Head Office Trivandrum",
    "id": "IN-ORG-kerala-co-operative-milk-marketing-feder"
  },
  "tender": {
    "id": "2026_KCMMF_852123_1",
    "title": "TENDER DOCUMENT FOR GROUP MEDICLAIM POLICY FOR EMPLOYEES 2026-2027",
    "status": "active",
    "procuringEntity": {
      "name": "Kerala Co-operative Milk Marketing Federation Ltd||Trivandrum Regional Co-operative Milk Producers Union Ltd||TRCMPU Ltd Head Office Trivandrum",
      "id": "IN-ORG-kerala-co-operative-milk-marketing-feder"
    },
    "mainProcurementCategory": "services",
    "value": {
      "amount": 20000000,
      "currency": "INR"
    },
    "tenderPeriod": {
      "endDate": "2026-06-11T00:00:00Z"
    },
    "description": "TENDER DOCUMENT FOR GROUP MEDICLAIM POLICY FOR EMPLOYEES 2026-2027"
  },
  "documents": [
    {
      "id": "woodpecker-kerala-2026_KCMMF_852123_1-0001-record",
      "documentType": "tenderNotice",
      "title": "Captured tender record (text) — 2026_KCMMF_852123_1",
      "url": "/files/c60aee38c6ac1ba0e4f416cebc26c17d7926443518976d9779fb8399e741e6ed.txt",
      "sourceUrl": "https://etenders.kerala.gov.in/nicgep/app?component=%24DirectLink&page=FrontEndListTendersbyDate&service=direct&session=T&sp=SOAf2kw%2BbmfdlG16%2B5h6lRQ%3D%3D",
      "sourceAlive": true,
      "sha256": "c60aee38c6ac1ba0e4f416cebc26c17d7926443518976d9779fb8399e741e6ed",
      "format": "text/plain",
      "textUrl": "/files/c60aee38c6ac1ba0e4f416cebc26c17d7926443518976d9779fb8399e741e6ed.txt",
      "extractionMethod": "raw"
    },
    {
      "id": "woodpecker-kerala-2026_KCMMF_852123_1-0001-doc-1",
      "documentType": "biddingDocuments",
      "title": "Tendernotice_1.pdf",
      "url": null,
      "sourceUrl": "https://etenders.kerala.gov.in/nicgep/app?component=%24DirectLink&page=FrontEndListTendersbyDate&service=direct&session=T&sp=SOAf2kw%2BbmfdlG16%2B5h6lRQ%3D%3D",
      "sourceAlive": false,
      "sha256": null,
      "format": "application/pdf",
      "textUrl": null,
      "extractionMethod": "none"
    }
  ]
}
