{
  "ocid": "woodpecker-kerala-2026_PWD_841496_4",
  "id": "woodpecker-kerala-2026_PWD_841496_4-0001",
  "date": "2026-05-29T00:00:00Z",
  "tag": [
    "tender"
  ],
  "initiationType": "tender",
  "buyer": {
    "name": "PWD||Chief Engineer (Buildings)||SE Bldgs (N)||EE Bldgs (KKD)||Buildings Subdivision Koyilandy",
    "id": "IN-ORG-pwd-chief-engineer-buildings-se-bldgs-n-"
  },
  "tender": {
    "id": "2026_PWD_841496_4",
    "title": "Running Contract",
    "status": "active",
    "procuringEntity": {
      "name": "PWD||Chief Engineer (Buildings)||SE Bldgs (N)||EE Bldgs (KKD)||Buildings Subdivision Koyilandy",
      "id": "IN-ORG-pwd-chief-engineer-buildings-se-bldgs-n-"
    },
    "mainProcurementCategory": "works",
    "value": {
      "amount": 211106,
      "currency": "INR"
    },
    "tenderPeriod": {
      "endDate": "2026-06-05T00:00:00Z"
    },
    "description": "Running Contract"
  },
  "documents": [
    {
      "id": "woodpecker-kerala-2026_PWD_841496_4-0001-record",
      "documentType": "tenderNotice",
      "title": "Captured tender record (text) — 2026_PWD_841496_4",
      "url": "/files/8f2fa5844c886c6e0834a9074d4e67147cc748886b77621235cae3a616318835.txt",
      "sourceUrl": "https://etenders.kerala.gov.in/nicgep/app?component=%24DirectLink&page=FrontEndListTendersbyDate&service=direct&session=T&sp=SOBgOvK77mZzzK9nHlotD8w%3D%3D",
      "sourceAlive": true,
      "sha256": "8f2fa5844c886c6e0834a9074d4e67147cc748886b77621235cae3a616318835",
      "format": "text/plain",
      "textUrl": "/files/8f2fa5844c886c6e0834a9074d4e67147cc748886b77621235cae3a616318835.txt",
      "extractionMethod": "raw"
    },
    {
      "id": "woodpecker-kerala-2026_PWD_841496_4-0001-doc-1",
      "documentType": "biddingDocuments",
      "title": "Tendernotice_1.pdf",
      "url": null,
      "sourceUrl": "https://etenders.kerala.gov.in/nicgep/app?component=%24DirectLink&page=FrontEndListTendersbyDate&service=direct&session=T&sp=SOBgOvK77mZzzK9nHlotD8w%3D%3D",
      "sourceAlive": false,
      "sha256": null,
      "format": "application/pdf",
      "textUrl": null,
      "extractionMethod": "none"
    }
  ]
}
