{
  "ocid": "woodpecker-jammukashmir-2026_PHE_310226_1",
  "id": "woodpecker-jammukashmir-2026_PHE_310226_1-0001",
  "date": "2026-05-18T00:00:00Z",
  "tag": [
    "tender"
  ],
  "initiationType": "tender",
  "buyer": {
    "name": "PHE||CE PHE Jammu||Hydraulic Circle Doda||Division Kishtwar",
    "id": "IN-ORG-phe-ce-phe-jammu-hydraulic-circle-doda-d"
  },
  "tender": {
    "id": "2026_PHE_310226_1",
    "title": "Refer to BOQ",
    "status": "active",
    "procuringEntity": {
      "name": "PHE||CE PHE Jammu||Hydraulic Circle Doda||Division Kishtwar",
      "id": "IN-ORG-phe-ce-phe-jammu-hydraulic-circle-doda-d"
    },
    "mainProcurementCategory": "works",
    "tenderPeriod": {
      "endDate": "2026-06-05T00:00:00Z"
    },
    "description": "Refer to BOQ"
  },
  "documents": [
    {
      "id": "woodpecker-jammukashmir-2026_PHE_310226_1-0001-record",
      "documentType": "tenderNotice",
      "title": "Captured tender record (text) — 2026_PHE_310226_1",
      "url": "/files/3db6c6799e79659bff9ae9eda9e219700aee95b39c0d2025d3bb969bb1c93cc9.txt",
      "sourceUrl": "https://jktenders.gov.in/nicgep/app?component=%24DirectLink&page=FrontEndListTendersbyDate&service=direct&session=T&sp=Sco9RZjwLRm9HvGhikIGELw%3D%3D",
      "sourceAlive": true,
      "sha256": "3db6c6799e79659bff9ae9eda9e219700aee95b39c0d2025d3bb969bb1c93cc9",
      "format": "text/plain",
      "textUrl": "/files/3db6c6799e79659bff9ae9eda9e219700aee95b39c0d2025d3bb969bb1c93cc9.txt",
      "extractionMethod": "raw"
    },
    {
      "id": "woodpecker-jammukashmir-2026_PHE_310226_1-0001-doc-1",
      "documentType": "biddingDocuments",
      "title": "Tendernotice_1.pdf",
      "url": null,
      "sourceUrl": "https://jktenders.gov.in/nicgep/app?component=%24DirectLink&page=FrontEndListTendersbyDate&service=direct&session=T&sp=Sco9RZjwLRm9HvGhikIGELw%3D%3D",
      "sourceAlive": false,
      "sha256": null,
      "format": "application/pdf",
      "textUrl": null,
      "extractionMethod": "none"
    }
  ]
}
